{
  "id": "http://castor-informatique.fr/questions/algorea_2017_1/collecting_gems",
  "version": "de.01",
  "authors": "Mathias Hiron",
  "translators": ["Robert Czechowski", "Wolfgang Pohl"],
  "title": "Edelsteine und Hindernisse",
  "intro": "Programmiere den Roboter:",
  "intros": {
    "easy": "",
    "medium": "",
    "hard": ""
  },
  "menu": ["Bedingte Anweisungen – Übungen", "Edelsteine und Hindernisse"],
  "sources": [
    "https://jwinf.de/task/1161",
    "https://jwinf.de/tasks/jwinf/jwinf-aufgaben/2017/17-FR-04-collecting-gems-2/index_new.html?channelId=task",
    "https://jwinf.de/tasks/jwinf/jwinf-aufgaben/2017/17-FR-04-collecting-gems-2/task_new.js"
  ],
  "gridInfos": {
    "bagSize": 8,
    "autoWithdraw": true,
    "hideSaveOrLoad": true,
    "conceptViewer": false,
    "contextType": "gems",
    "actionDelay": 200,
    "maxInstructions": {
      "easy": 8,
      "medium": 20,
      "hard": 15
    },
    "includeBlocks": {
      "groupByCategory": false,
      "generatedBlocks": {
        "robot": ["forward", "left", "right", "obstacleInFront"]
      },
      "standardBlocks": {
        "includeAll": false,
        "wholeCategories": [],
        "singleBlocks": {
          "easy": ["controls_if", "controls_repeat"],
          "medium": [
            "logic_negate",
            "controls_if",
            "controls_if_else",
            "controls_repeat"
          ],
          "hard": [
            "logic_negate",
            "controls_if",
            "controls_if_else",
            "controls_repeat"
          ]
        }
      },
      "pythonAdditionalFunctions": {
        "shared": ["range"]
      }
    },
    "blocklyColourTheme": "bwinf",
    "additionalBlocksByLevel": {
      "easy": {
        "generatedBlocks": {},
        "standardBlocks": {}
      },
      "medium": {
        "standardBlocks": {}
      }
    },
    "ignoreInvalidMoves": false,
    "checkEndEveryTurn": false
  },
  "data": {
    "easy": [
      {
        "tiles": [
          [1, 1, 1, 1, 1, 4, 1],
          [1, 1, 4, 1, 1, 3, 1],
          [1, 1, 4, 3, 4, 1, 1],
          [4, 4, 4, 4, 4, 1, 4],
          [1, 1, 1, 1, 1, 3, 1],
          [1, 3, 1, 3, 1, 1, 4],
          [1, 1, 1, 1, 1, 1, 1]
        ],
        "initItems": [
          {
            "row": 5,
            "col": 0,
            "dir": 0,
            "type": "robot"
          }
        ]
      }
    ],
    "medium": [
      {
        "tiles": [
          [1, 1, 1, 4, 1, 1, 1, 4, 1],
          [1, 1, 4, 1, 1, 3, 1, 3, 4],
          [1, 1, 1, 3, 1, 1, 4, 1, 1],
          [1, 1, 1, 1, 1, 4, 3, 1, 4],
          [1, 1, 1, 1, 1, 1, 1, 4, 1],
          [1, 1, 1, 1, 4, 4, 3, 1, 1],
          [4, 4, 4, 1, 3, 4, 1, 1, 1],
          [1, 1, 1, 4, 4, 4, 1, 1, 1],
          [1, 1, 1, 3, 1, 1, 3, 4, 1],
          [1, 1, 1, 1, 1, 1, 4, 1, 1]
        ],
        "initItems": [
          {
            "row": 8,
            "col": 0,
            "dir": 0,
            "type": "robot"
          }
        ]
      }
    ],
    "hard": [
      {
        "tiles": [
          [1, 1, 1, 1, 1, 1, 1, 1, 1, 1, 1, 1],
          [1, 1, 1, 1, 1, 4, 3, 1, 4, 1, 1, 1],
          [1, 1, 1, 3, 4, 4, 4, 4, 4, 4, 3, 1],
          [1, 1, 1, 1, 4, 4, 4, 4, 4, 4, 4, 1],
          [1, 1, 3, 4, 4, 4, 4, 4, 4, 4, 4, 1],
          [1, 1, 4, 4, 4, 4, 4, 4, 4, 3, 1, 1],
          [1, 1, 4, 4, 4, 4, 4, 4, 4, 4, 4, 1],
          [1, 1, 1, 4, 4, 4, 4, 4, 4, 4, 1, 1],
          [1, 1, 1, 3, 1, 4, 4, 4, 4, 3, 1, 1],
          [1, 1, 1, 1, 1, 1, 3, 1, 1, 1, 1, 1]
        ],
        "initItems": [
          {
            "row": 6,
            "col": 1,
            "dir": 3,
            "type": "robot"
          }
        ]
      }
    ]
  }
}
